_amplpy_cplex_swig.cpython-38-x86_64-linux-gnu.so
amplpy_cplex/.gitignore
amplpy_cplex/patch.py
amplpy_cplex/__init__.py
amplpy_cplex/cpp/ampls/CMakeLists.txt
amplpy_cplex/cpp/ampls/src/csvReader.h
amplpy_cplex/cpp/ampls/src/ampls.cpp
amplpy_cplex/cpp/ampls/src/csvReader.cpp
amplpy_cplex/cpp/ampls/include/ampls/ampls.h
amplpy_cplex/cpp/ampls/examples/loadModel.cpp
amplpy_cplex/cpp/ampls/examples/callbacks.cpp
amplpy_cplex/cpp/ampls/examples/benders.cpp
amplpy_cplex/cpp/ampls/examples/tsp.cpp
amplpy_cplex/cpp/ampls/examples/addEntities.cpp
amplpy_cplex/cpp/ampls/examples/getInformation.cpp
amplpy_cplex/cpp/ampls/examples/multipleSolutions.cpp
amplpy_cplex/cpp/ampls/examples/multipleModels.cpp
amplpy_cplex/cpp/ampls/examples/errorDetection.cpp
amplpy_cplex/cpp/ampls/examples/setOptions.cpp
amplpy_cplex/cpp/ampls/examples/cuttingStock.cpp
amplpy_cplex/cpp/ampls/examples/stoppingCriteria.cpp
amplpy_cplex/cpp/ampls/test/addEntities-test.cpp
amplpy_cplex/cpp/ampls/test/tsp-test.cpp
amplpy_cplex/cpp/ampls/test/multipleModels-test.cpp
amplpy_cplex/cpp/ampls/test/loadModel-test.cpp
amplpy_cplex/cpp/ampls/test/test-execute.h
amplpy_cplex/cpp/ampls/test/setOptions-test.cpp
amplpy_cplex/cpp/ampls/test/getInformation-test.cpp
amplpy_cplex/cpp/ampls/test/test-base.h
amplpy_cplex/cpp/ampls/test/errorDetection-test.cpp
amplpy_cplex/cpp/ampls/test/multipleSolutions-test.cpp
amplpy_cplex/cpp/ampls/test/cuttingStock-test.cpp
amplpy_cplex/cpp/ampls/swig/ampls-common.i
amplpy_cplex/cpp/cplex/src/cplex_interface.cpp
amplpy_cplex/cpp/cplex/src/cplex_callback.cpp
amplpy_cplex/cpp/cplex/include/cplex_callback.h
amplpy_cplex/cpp/cplex/include/cplex_interface.h
amplpy_cplex/cpp/cplex/examples/genericbranch-cplex.cpp
amplpy_cplex/cpp/cplex/examples/genericbranch-ampls.cpp
amplpy_cplex/cpp/cplex/test/cplex-test.cpp
amplpy_cplex/cpp/cplex/swig/cplex-common.i
amplpy_cplex/tests/test_cuttingstock.py
amplpy_cplex/tests/test_multiple_solutions.py
amplpy_cplex-0.2.1.dist-info/WHEEL
amplpy_cplex-0.2.1.dist-info/LICENSE
amplpy_cplex-0.2.1.dist-info/top_level.txt
amplpy_cplex-0.2.1.dist-info/RECORD
amplpy_cplex-0.2.1.dist-info/METADATA
